vlc_gesture_control/__init__.py
vlc_gesture_control/cli.py
vlc_gesture_control/config.py
vlc_gesture_control/gesture_detector.py
vlc_gesture_control/launcher.py
vlc_gesture_control/media_controller.py
vlc_gesture_control/setup_paths.py
vlc_gesture_control/vlc_m_cpu.py
vlc_gesture_control/vlc_m_gpu.py
vlc_gesture_control/tests/__init__.py
vlc_gesture_control/tests/conftest.py
vlc_gesture_control/tests/test_cli.py
vlc_gesture_control/tests/test_controller.py
vlc_gesture_control/tests/test_gesture_detector.py
vlc_gesture_control/tests/test_media_controller.py
vlc_gesture_control-1.1.2.dist-info/licenses/LICENSE
vlc_gesture_control-1.1.2.dist-info/METADATA
vlc_gesture_control-1.1.2.dist-info/WHEEL
vlc_gesture_control-1.1.2.dist-info/entry_points.txt
vlc_gesture_control-1.1.2.dist-info/top_level.txt
vlc_gesture_control-1.1.2.dist-info/RECORD
