Metadata-Version: 2.4
Name: vlc-gesture-control
Version: 1.1.2
Summary: Control VLC media player using hand gestures detected through a webcam
Author-email: ITIKELA BHASKAR <itikela.bhaskar@research.iiit.ac.in>
License-Expression: MIT
Project-URL: Homepage, https://github.com/BHASKAR1823/vlc_gesture_sontrol
Project-URL: Documentation, https://github.com/BHASKAR1823/vlc_gesture_sontrol/blob/main/COMPATIBILITY.md
Project-URL: Issue Tracker, https://github.com/BHASKAR1823/vlc_gesture_sontrol/issues
Keywords: vlc,gesture,control,computer vision,mediapipe
Classifier: Development Status :: 4 - Beta
Classifier: Intended Audience :: End Users/Desktop
Classifier: Programming Language :: Python :: 3
Classifier: Programming Language :: Python :: 3.9
Classifier: Programming Language :: Python :: 3.10
Classifier: Programming Language :: Python :: 3.11
Classifier: Programming Language :: Python :: 3.12
Classifier: Topic :: Multimedia :: Video :: Display
Classifier: Topic :: Utilities
Classifier: Operating System :: Microsoft :: Windows
Requires-Python: <3.13,>=3.9
License-File: LICENSE
Requires-Dist: opencv-python<5.0.0,>=4.8.0
Requires-Dist: mediapipe<0.11.0,>=0.10.8
Requires-Dist: pywin32<307,>=306
Requires-Dist: numpy<2.0.0,>=1.24.3
Requires-Dist: pyautogui<1.0.0,>=0.9.54
Provides-Extra: gpu
Requires-Dist: tensorflow<3.0.0,>=2.12.0; extra == "gpu"
Requires-Dist: torch<3.0.0,>=2.0.1; extra == "gpu"
Requires-Dist: torchvision<0.16.0,>=0.15.2; extra == "gpu"
Provides-Extra: dev
Requires-Dist: pytest<8.0.0,>=7.0.0; extra == "dev"
Requires-Dist: black==22.3.0; extra == "dev"
Requires-Dist: isort<6.0.0,>=5.12.0; extra == "dev"
Requires-Dist: flake8<7.0.0,>=6.0.0; extra == "dev"
Requires-Dist: mypy<2.0.0,>=1.0.0; extra == "dev"
Requires-Dist: pytest-cov<5.0.0,>=4.1.0; extra == "dev"
Dynamic: license-file
